beautifulplot/BarChart.py
beautifulplot/BoxPlot.py
beautifulplot/ScatterPlot.py
beautifulplot/__init__.py
beautifulplot-1.2.0.dist-info/METADATA
beautifulplot-1.2.0.dist-info/RECORD
beautifulplot-1.2.0.dist-info/WHEEL
beautifulplot-1.2.0.dist-info/top_level.txt
