Metadata-Version: 2.1
Name: beautifulplot
Version: 1.2.0
Summary: Make beautiful plot and statistical analysis effortless.
Home-page: https://git.benjamin-gallois.fr/bgallois/BeautifulPlot
Author: Benjamin Gallois
Author-email: benjamin.gallois@upmc.fr
License: GNU GENERAL PUBLIC LICENSE
Platform: UNKNOWN
Requires-Dist: matplotlib
Requires-Dist: numpy
Requires-Dist: scipy
